email_manager/__init__.py
email_manager/send_email.py
email_manager/config/__init__.py
email_manager/config/email_config.py
email_manager/factory/__init__.py
email_manager/factory/provider_factory.py
email_manager/providers/__init__.py
email_manager/providers/base.py
email_manager/providers/exceptions.py
email_manager/providers/mailgun_provider.py
email_manager/providers/mailtrap_provider.py
email_manager/providers/smtp_provider.py
email_manager/services/__init__.py
email_manager/services/notification_manager.py
email_manager/services/notification_service.py
email_manager-0.1.15.dist-info/METADATA
email_manager-0.1.15.dist-info/WHEEL
email_manager-0.1.15.dist-info/entry_points.txt
email_manager-0.1.15.dist-info/top_level.txt
email_manager-0.1.15.dist-info/RECORD
